helper_object/__init__.py
helper_object/funchelp.py
helper_object-0.1.5.dist-info/LICENSE
helper_object-0.1.5.dist-info/METADATA
helper_object-0.1.5.dist-info/WHEEL
helper_object-0.1.5.dist-info/top_level.txt
helper_object-0.1.5.dist-info/RECORD
