Metadata-Version: 2.1
Name: helper-object
Version: 0.1.5
Summary: Assistant for objects Python
Home-page: https://github.com/Beloslav13/helper-object
Author: Beloslav
Author-email: velislav1329@gmail.com
License: UNKNOWN
Platform: UNKNOWN
Classifier: Programming Language :: Python :: 3
Classifier: License :: OSI Approved :: MIT License
Classifier: Operating System :: OS Independent
Requires-Python: >=3.6
